crossdock/__init__.py
crossdock/main.py
crossdock/rand.py
crossdock/respw.py
crossdock/transport.py
crossdock/async/__init__.py
crossdock/async/client/__init__.py
crossdock/async/client/client.py
crossdock/async/client/behavior/__init__.py
crossdock/async/client/behavior/headers.py
crossdock/async/client/behavior/json.py
crossdock/async/client/behavior/raw.py
crossdock/async/client/behavior/thrift.py
crossdock/async/server/__init__.py
crossdock/async/server/server.py
crossdock/async/server/procedure/__init__.py
crossdock/async/server/procedure/error.py
crossdock/async/server/procedure/json.py
crossdock/async/server/procedure/phone.py
crossdock/async/server/procedure/raw.py
crossdock/async/server/procedure/thrift.py
crossdock/sync/__init__.py
crossdock/sync/client/__init__.py
crossdock/sync/client/client.py
crossdock/sync/client/behavior/__init__.py
crossdock/sync/client/behavior/headers.py
crossdock/sync/client/behavior/json.py
crossdock/sync/client/behavior/raw.py
crossdock/sync/client/behavior/thrift.py
yarpc/__init__.py
yarpc/_future.py
yarpc/errors.py
yarpc/rpc.py
yarpc/encoding/__init__.py
yarpc/encoding/_async.py
yarpc/encoding/_encoding.py
yarpc/encoding/json.py
yarpc/encoding/raw.py
yarpc/encoding/thrift.py
yarpc/sync/__init__.py
yarpc/sync/rpc.py
yarpc/testing/__init__.py
yarpc/testing/server.py
yarpc/transport/__init__.py
yarpc/transport/transport.py
yarpc/transport/validator.py
yarpc/transport/http/__init__.py
yarpc/transport/http/headers.py
yarpc/transport/http/inbound.py
yarpc/transport/http/outbound.py
yarpc/transport/tchannel/__init__.py
yarpc/transport/tchannel/headers.py
yarpc/transport/tchannel/inbound.py
yarpc/transport/tchannel/outbound.py
yarpc-0.7.0.dist-info/DESCRIPTION.rst
yarpc-0.7.0.dist-info/METADATA
yarpc-0.7.0.dist-info/RECORD
yarpc-0.7.0.dist-info/WHEEL
yarpc-0.7.0.dist-info/metadata.json
yarpc-0.7.0.dist-info/top_level.txt
