Metadata-Version: 2.0
Name: yarpc
Version: 0.7.0
Summary: ('YARPC for Python',)
Home-page: https://github.com/yarpc/yarpc-python
Author: Grayson Koonce
Author-email: grayson@uber.com
License: MIT
Platform: UNKNOWN
Requires-Dist: thriftrw (>=1.1,<2)
Requires-Dist: tornado (>=4.3,<5)
Provides-Extra: sync
Requires-Dist: futures; extra == 'sync'
Requires-Dist: threadloop (>=1,<2); extra == 'sync'
Provides-Extra: tchannel
Requires-Dist: tchannel (>=1.0.1,<2.0); extra == 'tchannel'
